{"geocoded_waypoints": [{"geocoder_status": "OK", "place_id": "ChIJTyY0BiK9oRQROQ3ahH85dSM", "types": ["establishment", "point_of_interest", "tourist_attraction"]}, {"geocoder_status": "OK", "place_id": "ChIJqd364hi9oRQR3XH2HVNePDI", "types": ["street_address"]}], "routes": [{"bounds": {"northeast": {"lat": 37.9747714, "lng": 23.7253463}, "southwest": {"lat": 37.9720309, "lng": 23.7219269}}, "copyrights": "Powered by Google, \u00a92026 Google", "legs": [{"distance": {"text": "0.8 km", "value": 812}, "duration": {"text": "14 mins", "value": 817}, "end_address": "Theorias 40, Athina 105 55, Greece", "end_location": {"lat": 37.9722535, "lng": 23.7234289}, "start_address": "Adrianou 11, Athina 105 55, Greece", "start_location": {"lat": 37.9747412, "lng": 23.7219269}, "steps": [{"distance": {"text": "0.8 km", "value": 812}, "duration": {"text": "14 mins", "value": 817}, "end_location": {"lat": 37.9722535, "lng": 23.7234289}, "html_instructions": "Walk to Theorias 40, Athina 105 55, Greece", "polyline": {"points": "c}wfFaexoCAGAIAQB@@?H@P@LAFABA@ABE?G?CAG?KC[?K?GBMB_@?O?I?KCMAGAG?AAAA?AAC?C?Q@O??O?m@Ak@?m@XKLENGVMVOVODEZS@EBEEIECEEG?SBEAESAECSAW?M?M@Q@a@BKF@ZBPBP@L@@?L@LDD@DDDHDBTD@ABA?C@C?E@C?A@?@?V@B?b@@b@?H?DXBPJh@FXDPBHFTBFFRHRJZDHFNLTBDRXFHSXIAC?G@A?"}, "start_location": {"lat": 37.9747412, "lng": 23.7219269}, "steps": [{"distance": {"text": "16 m", "value": 16}, "duration": {"text": "1 min", "value": 14}, "end_location": {"lat": 37.9747714, "lng": 23.7221094}, "html_instructions": "Head <b>east</b>", "polyline": {"points": "c}wfFaexoCAGAIAQ"}, "start_location": {"lat": 37.9747412, "lng": 23.7219269}, "travel_mode": "WALKING"}, {"distance": {"text": "42 m", "value": 42}, "duration": {"text": "1 min", "value": 39}, "end_location": {"lat": 37.9744375, "lng": 23.7221928}, "html_instructions": "Turn <b>right</b>", "maneuver": "turn-right", "polyline": {"points": "i}wfFefxoCB@@?H@P@LAFABA@ABE?G"}, "start_location": {"lat": 37.9747714, "lng": 23.7221094}, "travel_mode": "WALKING"}, {"distance": {"text": "0.1 km", "value": 110}, "duration": {"text": "2 mins", "value": 93}, "end_location": {"lat": 37.974707, "lng": 23.7231397}, "html_instructions": "Turn <b>left</b> toward <b>\u039f\u03b4\u03cc\u03c2 \u03c4\u03c9\u03bd \u03a0\u03b1\u03bd\u03b1\u03b8\u03b7\u03bd\u03b1\u03af\u03c9\u03bd</b>", "maneuver": "turn-left", "polyline": {"points": "g{wfFufxoC?CAG?KC[?K?GBMB_@?O?I?KCMAGAG?AAAA?AAC?C?Q@O?"}, "start_location": {"lat": 37.9744375, "lng": 23.7221928}, "travel_mode": "WALKING"}, {"distance": {"text": "67 m", "value": 67}, "duration": {"text": "1 min", "value": 58}, "end_location": {"lat": 37.97472339999999, "lng": 23.7238995}, "html_instructions": "Turn <b>right</b> toward <b>\u039f\u03b4\u03cc\u03c2 \u03c4\u03c9\u03bd \u03a0\u03b1\u03bd\u03b1\u03b8\u03b7\u03bd\u03b1\u03af\u03c9\u03bd</b>", "maneuver": "turn-right", "polyline": {"points": "}|wfFslxoC?O?m@Ak@?m@"}, "start_location": {"lat": 37.974707, "lng": 23.7231397}, "travel_mode": "WALKING"}, {"distance": {"text": "0.1 km", "value": 106}, "duration": {"text": "2 mins", "value": 112}, "end_location": {"lat": 37.9738844, "lng": 23.7244535}, "html_instructions": "Turn <b>right</b> onto <b>\u039f\u03b4\u03cc\u03c2 \u03c4\u03c9\u03bd \u03a0\u03b1\u03bd\u03b1\u03b8\u03b7\u03bd\u03b1\u03af\u03c9\u03bd</b>", "maneuver": "turn-right", "polyline": {"points": "_}wfFkqxoCXKLENGVMVOVODEZS@EBE"}, "start_location": {"lat": 37.97472339999999, "lng": 23.7238995}, "travel_mode": "WALKING"}, {"distance": {"text": "0.1 km", "value": 104}, "duration": {"text": "2 mins", "value": 91}, "end_location": {"lat": 37.9741708, "lng": 23.7253463}, "html_instructions": "Turn <b>left</b> onto <b>Polignotou</b>", "maneuver": "turn-left", "polyline": {"points": "wwwfFytxoCEIECEEG?SBEAESAECSAW?M?M@Q@a@BK"}, "start_location": {"lat": 37.9738844, "lng": 23.7244535}, "travel_mode": "WALKING"}, {"distance": {"text": "82 m", "value": 82}, "duration": {"text": "2 mins", "value": 94}, "end_location": {"lat": 37.9734745, "lng": 23.7251263}, "html_instructions": "Turn <b>right</b> onto <b>Dioskouron</b>", "maneuver": "turn-right", "polyline": {"points": "qywfFmzxoCF@ZBPBP@L@@?L@LDD@DDDHDB"}, "start_location": {"lat": 37.9741708, "lng": 23.7253463}, "travel_mode": "WALKING"}, {"distance": {"text": "89 m", "value": 89}, "duration": {"text": "2 mins", "value": 132}, "end_location": {"lat": 37.97274000000001, "lng": 23.7251978}, "html_instructions": "Slight <b>left</b> to stay on <b>Dioskouron</b><div style=\"font-size:0.9em\">Take the stairs</div>", "maneuver": "turn-slight-left", "polyline": {"points": "euwfFayxoCTD@ABA?C@C?E@C?A@?@?V@B?b@@b@?H?"}, "start_location": {"lat": 37.9734745, "lng": 23.7251263}, "travel_mode": "WALKING"}, {"distance": {"text": "0.2 km", "value": 166}, "duration": {"text": "3 mins", "value": 153}, "end_location": {"lat": 37.9720309, "lng": 23.7235607}, "html_instructions": "Turn <b>right</b> onto <b>Theorias</b>", "maneuver": "turn-right", "polyline": {"points": "spwfFoyxoCDXBPJh@FXDPBHFTBFFRHRJZDHFNLTBDRXFH"}, "start_location": {"lat": 37.97274000000001, "lng": 23.7251978}, "travel_mode": "WALKING"}, {"distance": {"text": "16 m", "value": 16}, "duration": {"text": "1 min", "value": 13}, "end_location": {"lat": 37.972131, "lng": 23.7234269}, "html_instructions": "Turn <b>right</b>", "maneuver": "turn-right", "polyline": {"points": "elwfFgoxoCSX"}, "start_location": {"lat": 37.9720309, "lng": 23.7235607}, "travel_mode": "WALKING"}, {"distance": {"text": "14 m", "value": 14}, "duration": {"text": "1 min", "value": 18}, "end_location": {"lat": 37.9722535, "lng": 23.7234289}, "html_instructions": "Turn <b>right</b><div style=\"font-size:0.9em\">Take the stairs</div>", "maneuver": "turn-right", "polyline": {"points": "ylwfFmnxoCIAC?G@A?"}, "start_location": {"lat": 37.972131, "lng": 23.7234269}, "travel_mode": "WALKING"}], "travel_mode": "WALKING"}], "traffic_speed_entry": [], "via_waypoint": []}], "overview_polyline": {"points": "c}wfFaexoCCQAQB@J@^?PKA_@Cg@BUBo@?UG_@ICU@O??OAyA?m@XK\\Mn@]z@o@BEEIKI[BEAESEYAe@FmAfAJj@HVTVBBEBO^@fA@H?DXNz@Lj@Vz@b@hAl@~@SXIAK@A?"}, "summary": "Dioskouron", "warnings": ["Walking directions are in beta. Use caution \u2013 This route may be missing sidewalks or pedestrian paths."], "waypoint_order": []}], "status": "OK"}