{"geocoded_waypoints": [{"geocoder_status": "OK", "place_id": "ChIJnzODwAJUKhMRaIgFQ-PV5U4", "types": ["street_address", "subpremise"]}, {"geocoder_status": "OK", "place_id": "ChIJh5yKfkpVKhMRdcrN42QXDaY", "types": ["establishment", "point_of_interest"]}, {"geocoder_status": "OK", "place_id": "ChIJ91uP8wZUKhMRwxwKcKu-zW0", "types": ["street_address", "subpremise"]}, {"geocoder_status": "OK", "place_id": "ChIJaWUSfgJUKhMRc1-yg2X8qVQ", "types": ["street_address", "subpremise"]}], "routes": [{"bounds": {"northeast": {"lat": 43.7771309, "lng": 11.2664682}, "southwest": {"lat": 43.76947089999999, "lng": 11.2534368}}, "copyrights": "Powered by Google, \u00a92026 Google", "legs": [{"distance": {"text": "1.4 km", "value": 1369}, "duration": {"text": "19 mins", "value": 1116}, "end_address": "Via dei Macci, 115 rosso, 50122 Firenze FI, Italy", "end_location": {"lat": 43.7711702, "lng": 11.2663433}, "start_address": "Via Sant'Antonino, 76, 50123 Firenze FI, Italy", "start_location": {"lat": 43.7763056, "lng": 11.253703}, "steps": [{"distance": {"text": "55 m", "value": 55}, "duration": {"text": "1 min", "value": 45}, "end_location": {"lat": 43.776574, "lng": 11.2542505}, "html_instructions": "Head <b>northeast</b> on <b>Via Sant'Antonino</b> toward <b>Piazza del Mercato Centrale</b>", "polyline": {"points": "}`ejGs~tcAAGSg@GUUg@"}, "start_location": {"lat": 43.7763056, "lng": 11.253703}, "travel_mode": "WALKING"}, {"distance": {"text": "9 m", "value": 9}, "duration": {"text": "1 min", "value": 7}, "end_location": {"lat": 43.7765269, "lng": 11.2543489}, "html_instructions": "Turn <b>right</b> onto <b>Piazza del Mercato Centrale</b>", "maneuver": "turn-right", "polyline": {"points": "qbejGabucADK@G"}, "start_location": {"lat": 43.776574, "lng": 11.2542505}, "travel_mode": "WALKING"}, {"distance": {"text": "48 m", "value": 48}, "duration": {"text": "1 min", "value": 40}, "end_location": {"lat": 43.77670699999999, "lng": 11.254851}, "html_instructions": "<b>Piazza del Mercato Centrale</b> turns <b>left</b> and becomes <b>Via Rosina</b>", "polyline": {"points": "ibejGubucA?E?A?EACAG_@iA"}, "start_location": {"lat": 43.7765269, "lng": 11.2543489}, "travel_mode": "WALKING"}, {"distance": {"text": "75 m", "value": 75}, "duration": {"text": "1 min", "value": 63}, "end_location": {"lat": 43.7763265, "lng": 11.2556802}, "html_instructions": "Turn <b>right</b> onto <b>Via Taddea</b>", "maneuver": "turn-right", "polyline": {"points": "mcejGyeucATe@DS`@gAJW@K"}, "start_location": {"lat": 43.77670699999999, "lng": 11.254851}, "travel_mode": "WALKING"}, {"distance": {"text": "0.1 km", "value": 97}, "duration": {"text": "1 min", "value": 77}, "end_location": {"lat": 43.7771309, "lng": 11.2562466}, "html_instructions": "Turn <b>left</b> onto <b>Via de' Ginori</b>", "maneuver": "turn-left", "polyline": {"points": "aaejG_kucA_@SQKKGAA_@U]UUOKK"}, "start_location": {"lat": 43.7763265, "lng": 11.2556802}, "travel_mode": "WALKING"}, {"distance": {"text": "0.1 km", "value": 98}, "duration": {"text": "1 min", "value": 83}, "end_location": {"lat": 43.7767259, "lng": 11.2574004}, "html_instructions": "Turn <b>right</b> onto <b>Via Guelfa</b>", "maneuver": "turn-right", "polyline": {"points": "afejGqnucATaA`@}AHYDQFY"}, "start_location": {"lat": 43.7771309, "lng": 11.2562466}, "travel_mode": "WALKING"}, {"distance": {"text": "0.6 km", "value": 603}, "duration": {"text": "8 mins", "value": 490}, "end_location": {"lat": 43.7738856, "lng": 11.2636485}, "html_instructions": "Continue onto <b>Via degli Alfani</b>", "polyline": {"points": "qcejGwuucAdAeD@CHWnAwD@CHWXw@DMXy@BId@qARg@tB}FFQVq@DMtBwF"}, "start_location": {"lat": 43.7767259, "lng": 11.2574004}, "travel_mode": "WALKING"}, {"distance": {"text": "0.3 km", "value": 327}, "duration": {"text": "4 mins", "value": 264}, "end_location": {"lat": 43.7717022, "lng": 11.2662884}, "html_instructions": "Continue onto <b>Via dei Pilastri</b>", "polyline": {"points": "yqdjGy|vcAHGd@m@NSvAiBDGnAcBNSxBsCZc@VYHI"}, "start_location": {"lat": 43.7738856, "lng": 11.2636485}, "travel_mode": "WALKING"}, {"distance": {"text": "26 m", "value": 26}, "duration": {"text": "1 min", "value": 22}, "end_location": {"lat": 43.7714299, "lng": 11.2664682}, "html_instructions": "Continue onto <b>Piazza Sant'Ambrogio</b>", "polyline": {"points": "cddjGimwcAJYJJ\\U"}, "start_location": {"lat": 43.7717022, "lng": 11.2662884}, "travel_mode": "WALKING"}, {"distance": {"text": "31 m", "value": 31}, "duration": {"text": "1 min", "value": 25}, "end_location": {"lat": 43.7711702, "lng": 11.2663433}, "html_instructions": "Turn <b>right</b> onto <b>Via dei Macci</b><div style=\"font-size:0.9em\">Destination will be on the right</div>", "maneuver": "turn-right", "polyline": {"points": "mbdjGmnwcAHDFBHDJBJD"}, "start_location": {"lat": 43.7714299, "lng": 11.2664682}, "travel_mode": "WALKING"}], "traffic_speed_entry": [], "via_waypoint": []}, {"distance": {"text": "0.6 km", "value": 619}, "duration": {"text": "9 mins", "value": 510}, "end_address": "Via Ghibellina, 146, 50122 Firenze FI, Italy", "end_location": {"lat": 43.7704444, "lng": 11.2604899}, "start_address": "Via dei Macci, 115 rosso, 50122 Firenze FI, Italy", "start_location": {"lat": 43.7711702, "lng": 11.2663433}, "steps": [{"distance": {"text": "0.2 km", "value": 207}, "duration": {"text": "3 mins", "value": 168}, "end_location": {"lat": 43.76947089999999, "lng": 11.2654095}, "html_instructions": "Head <b>south</b> on <b>Via dei Macci</b> toward <b>Via Andrea del Verrocchio</b>", "polyline": {"points": "y`djGsmwcAB?BHHDHBn@Xl@V`@NLFHBx@^FB|Ar@"}, "start_location": {"lat": 43.7711702, "lng": 11.2663433}, "travel_mode": "WALKING"}, {"distance": {"text": "0.4 km", "value": 412}, "duration": {"text": "6 mins", "value": 342}, "end_location": {"lat": 43.7704444, "lng": 11.2604899}, "html_instructions": "Turn <b>right</b> onto <b>Via Ghibellina</b><div style=\"font-size:0.9em\">Destination will be on the right</div>", "maneuver": "turn-right", "polyline": {"points": "evcjGygwcAWnBMhAETALOlACNAJ@LGT_@`DCDY|BAFQ|AALYlCGb@?HAT"}, "start_location": {"lat": 43.76947089999999, "lng": 11.2654095}, "travel_mode": "WALKING"}], "traffic_speed_entry": [], "via_waypoint": []}, {"distance": {"text": "1.0 km", "value": 1035}, "duration": {"text": "14 mins", "value": 838}, "end_address": "Piazza di Madonna degli Aldobrandini, 6, 50123 Firenze FI, Italy", "end_location": {"lat": 43.7753265, "lng": 11.2534368}, "start_address": "Via Ghibellina, 146, 50122 Firenze FI, Italy", "start_location": {"lat": 43.7704444, "lng": 11.2604899}, "steps": [{"distance": {"text": "0.2 km", "value": 212}, "duration": {"text": "3 mins", "value": 175}, "end_location": {"lat": 43.7706558, "lng": 11.2579047}, "html_instructions": "Head <b>west</b> on <b>Via Ghibellina</b> toward <b>Via del Crocifisso</b>", "polyline": {"points": "g|cjGaivcACd@?HCt@ARGpAMnC@JM|C"}, "start_location": {"lat": 43.7704444, "lng": 11.2604899}, "travel_mode": "WALKING"}, {"distance": {"text": "0.2 km", "value": 215}, "duration": {"text": "3 mins", "value": 180}, "end_location": {"lat": 43.7726048, "lng": 11.2578917}, "html_instructions": "Turn <b>right</b> onto <b>Via del Proconsolo</b>", "maneuver": "turn-right", "polyline": {"points": "s}cjG{xucAc@GK@C?G?i@A{@AGCs@@u@BYBM?U@E?]@M@"}, "start_location": {"lat": 43.7706558, "lng": 11.2579047}, "travel_mode": "WALKING"}, {"distance": {"text": "0.1 km", "value": 122}, "duration": {"text": "2 mins", "value": 98}, "end_location": {"lat": 43.77353979999999, "lng": 11.257213}, "html_instructions": "Continue straight onto <b>Piazza del Duomo</b>", "maneuver": "straight", "polyline": {"points": "widjGyxucA?H}A^E@G@IDC@CBCBCBA@CBm@z@AB"}, "start_location": {"lat": 43.7726048, "lng": 11.2578917}, "travel_mode": "WALKING"}, {"distance": {"text": "85 m", "value": 85}, "duration": {"text": "1 min", "value": 69}, "end_location": {"lat": 43.7740943, "lng": 11.257853}, "html_instructions": "Turn <b>right</b> onto <b>Via dei Servi</b>", "maneuver": "turn-right", "polyline": {"points": "sodjGqtucAmB_C"}, "start_location": {"lat": 43.77353979999999, "lng": 11.257213}, "travel_mode": "WALKING"}, {"distance": {"text": "0.2 km", "value": 179}, "duration": {"text": "2 mins", "value": 142}, "end_location": {"lat": 43.77474410000001, "lng": 11.2558958}, "html_instructions": "Turn <b>left</b> onto <b>Via de' Pucci</b>", "maneuver": "turn-left", "polyline": {"points": "asdjGqxucAGJ}@dEGRs@~C"}, "start_location": {"lat": 43.7740943, "lng": 11.257853}, "travel_mode": "WALKING"}, {"distance": {"text": "65 m", "value": 65}, "duration": {"text": "1 min", "value": 51}, "end_location": {"lat": 43.77499, "lng": 11.2551726}, "html_instructions": "Continue onto <b>Via de' Gori</b>", "polyline": {"points": "cwdjGklucAETQt@YdA"}, "start_location": {"lat": 43.77474410000001, "lng": 11.2558958}, "travel_mode": "WALKING"}, {"distance": {"text": "0.1 km", "value": 99}, "duration": {"text": "1 min", "value": 78}, "end_location": {"lat": 43.7753692, "lng": 11.2540386}, "html_instructions": "Continue onto <b>Piazza di San Lorenzo</b>", "polyline": {"points": "uxdjGygucACTSz@IPEPCH_@`B"}, "start_location": {"lat": 43.77499, "lng": 11.2551726}, "travel_mode": "WALKING"}, {"distance": {"text": "58 m", "value": 58}, "duration": {"text": "1 min", "value": 45}, "end_location": {"lat": 43.7753265, "lng": 11.2534368}, "html_instructions": "Continue onto <b>Via del Canto dei Nelli</b><div style=\"font-size:0.9em\">Destination will be on the left</div>", "polyline": {"points": "a{djGw`ucAAFI\\CLET\\l@"}, "start_location": {"lat": 43.7753692, "lng": 11.2540386}, "travel_mode": "WALKING"}], "traffic_speed_entry": [], "via_waypoint": []}], "overview_polyline": {"points": "}`ejGs~tcAs@mBFS?Gc@{ATe@DSl@_B@K_@S]SuA}@KKTaAj@wBtAuEdBkF|@iCvDiK\\_AtBwFHGt@aA|AqBtFoH`@c@JYJJ\\UHDPHVHFHpBz@rBz@dBv@e@xD[`C?Xg@vDq@hFc@hEIzBU`GM|Cc@GO@q@A{@AGCiBDg@BgAD?H}A^MBUNw@dAABmB_CGJ}@dE{@rDWjAYdACTSz@IPIZa@hBMj@ET\\l@"}, "summary": "Via degli Alfani", "warnings": ["Walking directions are in beta. Use caution \u2013 This route may be missing sidewalks or pedestrian paths."], "waypoint_order": [0, 1]}], "status": "OK"}