{"geocoded_waypoints": [{"geocoder_status": "OK", "place_id": "ChIJATr1n-Fx5kcRjQb6q6cdQDY", "types": ["church", "establishment", "place_of_worship", "point_of_interest", "tourist_attraction"]}, {"geocoder_status": "OK", "place_id": "ChIJa4GQZFtx5kcRAZWQg58A4nY", "types": ["cafe", "establishment", "food", "point_of_interest"]}], "routes": [{"bounds": {"northeast": {"lat": 48.8535697, "lng": 2.3501222}, "southwest": {"lat": 48.8522553, "lng": 2.3472296}}, "copyrights": "Powered by Google, \u00a92026 Google", "legs": [{"distance": {"text": "0.3 km", "value": 323}, "duration": {"text": "5 mins", "value": 275}, "end_address": "37 Rue de la B\u00fbcherie, 75005 Paris, France", "end_location": {"lat": 48.85262909999999, "lng": 2.3472296}, "start_address": "6 Parvis Notre-Dame - Pl. Jean-Paul II, 75004 Paris, France", "start_location": {"lat": 48.85330399999999, "lng": 2.3501222}, "steps": [{"distance": {"text": "0.3 km", "value": 323}, "duration": {"text": "5 mins", "value": 275}, "end_location": {"lat": 48.85262909999999, "lng": 2.3472296}, "html_instructions": "Walk to 37 Rue de la B\u00fbcherie, 75005 Paris, France", "polyline": {"points": "ctdiHg_jMKb@[tAIb@CLDTtA`AZRd@Zp@d@BBDBFBHUDBPN@@ELER@BAHBh@C@A@A??@A@AB?@AB?@?@A@?@?@?@?@@BKDGFCJCBCHBFGHCHITAB"}, "start_location": {"lat": 48.85330399999999, "lng": 2.3501222}, "steps": [{"distance": {"text": "75 m", "value": 75}, "duration": {"text": "1 min", "value": 61}, "end_location": {"lat": 48.8535697, "lng": 2.3492594}, "html_instructions": "Head <b>northwest</b> on <b>Rue du Cloitre Notre Dame</b> toward <b>Rue d'Arcole</b>", "polyline": {"points": "ctdiHg_jMKb@[tAIb@CL"}, "start_location": {"lat": 48.85330399999999, "lng": 2.3501222}, "travel_mode": "WALKING"}, {"distance": {"text": "0.2 km", "value": 152}, "duration": {"text": "2 mins", "value": 122}, "end_location": {"lat": 48.85236039999999, "lng": 2.3484182}, "html_instructions": "Turn <b>left</b> onto <b>Pont au Double</b>", "maneuver": "turn-left", "polyline": {"points": "yudiH{yiMDTtA`AZRd@Zp@d@BBDBFBHUDB"}, "start_location": {"lat": 48.8535697, "lng": 2.3492594}, "travel_mode": "WALKING"}, {"distance": {"text": "8 m", "value": 8}, "duration": {"text": "1 min", "value": 18}, "end_location": {"lat": 48.8523127, "lng": 2.3481391}, "html_instructions": "Continue onto <b>Rue Lagrange</b>", "polyline": {"points": "gndiHstiMPN@@ELER@B"}, "start_location": {"lat": 48.85236039999999, "lng": 2.3484182}, "travel_mode": "WALKING"}, {"distance": {"text": "24 m", "value": 24}, "duration": {"text": "1 min", "value": 20}, "end_location": {"lat": 48.8522982, "lng": 2.3478831}, "html_instructions": "Turn <b>right</b> toward <b>Rue de la B\u00fbcherie</b>", "maneuver": "turn-right", "polyline": {"points": "}mdiH{riMAHBh@"}, "start_location": {"lat": 48.8523127, "lng": 2.3481391}, "travel_mode": "WALKING"}, {"distance": {"text": "45 m", "value": 45}, "duration": {"text": "1 min", "value": 37}, "end_location": {"lat": 48.852506, "lng": 2.3474572}, "html_instructions": "Turn <b>right</b> toward <b>Rue de la B\u00fbcherie</b>", "maneuver": "turn-right", "polyline": {"points": "{mdiHgqiMC@A@A??@A@AB?@AB?@?@A@?@?@?@?@@BKDGFCJCBCHBF"}, "start_location": {"lat": 48.8522982, "lng": 2.3478831}, "travel_mode": "WALKING"}, {"distance": {"text": "19 m", "value": 19}, "duration": {"text": "1 min", "value": 17}, "end_location": {"lat": 48.85262909999999, "lng": 2.3472296}, "html_instructions": "Continue onto <b>Rue de la B\u00fbcherie</b><div style=\"font-size:0.9em\">Destination will be on the left</div>", "polyline": {"points": "eodiHsniMGHCHITAB"}, "start_location": {"lat": 48.852506, "lng": 2.3474572}, "travel_mode": "WALKING"}], "travel_mode": "WALKING"}], "traffic_speed_entry": [], "via_waypoint": []}], "overview_polyline": {"points": "ctdiHg_jMu@jDDTtA`A`An@bAp@HUDBRPK`@?LBh@C@A@CBADCP@BKDKRGLBFGHM^AB"}, "summary": "Rue du Cloitre Notre Dame", "warnings": ["Walking directions are in beta. Use caution \u2013 This route may be missing sidewalks or pedestrian paths."], "waypoint_order": []}], "status": "OK"}